job_template/__init__.py
job_template/admin.py
job_template/apps.py
job_template/constants.py
job_template/models.py
job_template/tasks.py
job_template/template.py
job_template/utils.py
job_template/management/commands/populate_job_status_constants.py
job_template/migrations/0001_initial.py
job_template/migrations/__init__.py
job_template-1.3.dist-info/METADATA
job_template-1.3.dist-info/WHEEL
job_template-1.3.dist-info/top_level.txt
job_template-1.3.dist-info/RECORD
