Metadata-Version: 2.4
Name: job_template
Version: 1.3
Summary: A Django app for job-template
Author-email: Harsh Biyani <harsh.b@lendenclub.com>
Requires-Python: >=3.12
Requires-Dist: django>=5.1
